perfect_package/__init__.py
perfect_package/stub.py
perfect_package-0.2.0.dist-info/LICENSE
perfect_package-0.2.0.dist-info/METADATA
perfect_package-0.2.0.dist-info/WHEEL
perfect_package-0.2.0.dist-info/RECORD
